pypom_axe/__init__.py
pypom_axe/axe.py
pypom_axe/src/axe.min.js
pypom_axe-0.1.1.dist-info/DESCRIPTION.rst
pypom_axe-0.1.1.dist-info/METADATA
pypom_axe-0.1.1.dist-info/RECORD
pypom_axe-0.1.1.dist-info/WHEEL
pypom_axe-0.1.1.dist-info/metadata.json
pypom_axe-0.1.1.dist-info/top_level.txt
