Metadata-Version: 2.0
Name: pypom-axe
Version: 0.1.1
Summary: pypom-axe is a PyPOM extension to integrate                 accessibility tests using the aXe API.
Home-page: https://github.com/kimberlythegeek/pypom-axe
Author: Kimberly Sereduck
Author-email: ksereduck@mozilla.com
License: Mozilla Public License 2.0 (MPL 2.0)
Keywords: axe-core pypom accessibility automation mozilla
Platform: UNKNOWN
Requires-Dist: pypom (>=1.2.0)
